[
  {
    "quantity": 5,
    "drink": "TEA",
    "status": true
  },
  {
    "quantity": 5,
    "drink": "COFFEE",
    "status": true
  },
  {
    "quantity": 4,
    "drink": "TEA",
    "status": true
  },
  {
    "quantity": 3,
    "drink": "BLACK_TEA",
    "status": true
  },
  {
    "quantity": 3,
    "drink": "COFFEE",
    "status": true
  },
  {
    "quantity": 1,
    "drink": "BLACK_COFFEE",
    "status": true
  },
  {
    "quantity": 1,
    "drink": "COFFEE",
    "status": true
  },
  {
    "quantity": 5,
    "drink": "COFFEE",
    "status": true
  },
  {
    "quantity": 5,
    "drink": "COFFEE",
    "status": true
  },
  {
    "quantity": 10,
    "drink": "COFFEE",
    "status": true
  },
  {
    "quantity": 5,
    "drink": "TEA",
    "status": true
  },
  {
    "quantity": 7,
    "drink": "BLACK_COFFEE",
    "status": true
  }
]